week3/ALU.v
`timescale 1 ns/100ps
//-TestBench-
module alu_test();
  reg [7:0]A;
  reg [7:0]B;
  wire [7:0]out;
  reg [2:0]OP;

  
  alu test(A,B,OP,out);
  
  
  initial
    begin
      #100
      A = 8'b0; B = 8'b0; OP = 3'b000;
      #600 A = 8'b00000111; B = 8'b00000001; OP = 3'b000;
      #600 A = 8'b00000011; B = 8'b00000001; OP = 3'b001;
      #600 A = 8'b00001011; B = 8'b00000001; OP = 3'b010;
      #600 A = 8'b00000011; B = 8'b00000001; OP = 3'b011;
      #600 A = 8'b00010011; B = 8'b00000001; OP = 3'b100;
      #600 A = 8'b00000011; B = 8'b00001000; OP = 3'b101;
      #600 A = 8'b00000011; B = 8'b00000001; OP = 3'b110;
      #600 A = 8'b00010000; B = 8'b00000001; OP = 3'b111;
    end
initial #9000 $finish;
initial $dumpvars;
initial begin
     $display("====== show simulation ==========");
		 $monitor("time: %4d %b(A) %b %b(B) out = %b \n",$time, A, OP, B, out);
		 end
endmodule


//ALU model
module alu (
Data_A, // I 8-bit : first input signal
Data_B, // I 8-bit : second input signal
OP_Code, // I 3-bit : operation
Data_Out // I 16-bit : result
);
input [7:0] Data_A, Data_B;
input [2:0] OP_Code;
output [7:0] Data_Out;
reg [7:0] Data_Out;
always@(Data_A or Data_B or OP_Code) begin
case (OP_Code)
	3'b000: Data_Out = 8'b0;
	3'b001: Data_Out = Data_A & Data_B;
	3'b010: Data_Out = Data_A | Data_B;
	3'b011: Data_Out = Data_A ^ Data_B;
	3'b100: Data_Out = ~Data_A;
	3'b101: Data_Out = Data_A - Data_B;
	3'b110: Data_Out = Data_A + Data_B;
	3'b111: Data_Out = 8'hFF;
default : Data_Out = 16'b0;
endcase
end
endmodule

week3/dump.vcd
$date
	Fri Oct 18 13:35:30 2019
$end
$version
	Icarus Verilog
$end
$timescale
	100ps
$end
$scope module alu_test $end
$var wire 8 ! out [7:0] $end
$var reg 8 " A [7:0] $end
$var reg 8 # B [7:0] $end
$var reg 3 $ OP [2:0] $end
$scope module test $end
$var wire 8 % Data_A [7:0] $end
$var wire 8 & Data_B [7:0] $end
$var wire 3 ' OP_Code [2:0] $end
$var reg 8 ( Data_Out [7:0] $end
$upscope $end
$upscope $end
$enddefinitions $end
#0
$dumpvars
bx (
bx '
bx &
bx %
bx $
bx #
bx "
bx !
$end
#1000
b0 !
b0 (
b0 $
b0 '
b0 #
b0 &
b0 "
b0 %
#7000
b1 #
b1 &
b111 "
b111 %
#13000
b1 !
b1 (
b1 $
b1 '
b11 "
b11 %
#19000
b1011 !
b1011 (
b10 $
b10 '
b1011 "
b1011 %
#25000
b10 !
b10 (
b11 $
b11 '
b11 "
b11 %
#31000
b11101100 !
b11101100 (
b100 $
b100 '
b10011 "
b10011 %
#37000
b11111011 !
b11111011 (
b101 $
b101 '
b1000 #
b1000 &
b11 "
b11 %
#43000
b100 !
b100 (
b110 $
b110 '
b1 #
b1 &
#49000
b11111111 !
b11111111 (
b111 $
b111 '
b10000 "
b10000 %
